oleshko_excel/__init__.py
oleshko_excel/excel.py
oleshkooo_excel-0.0.1.dist-info/LICENSE
oleshkooo_excel-0.0.1.dist-info/METADATA
oleshkooo_excel-0.0.1.dist-info/WHEEL
oleshkooo_excel-0.0.1.dist-info/top_level.txt
oleshkooo_excel-0.0.1.dist-info/RECORD
